<?xml version="1.0" encoding="UTF-8"?>
<OpenSearchDescription xmlns="http://a9.com/-/spec/opensearch/1.1/">
  <ShortName>Activ Automobiles</ShortName>
  <Description>Recherchez parmi plus de 800 voitures d'occasion chez Activ Automobiles</Description>
  <Tags>voiture occasion automobile achat</Tags>
  <Contact>contact@activ-automobiles.fr</Contact>
  <Url type="text/html" template="https://www.activ-automobiles.fr/voitures-occasion?q={searchTerms}"/>
  <Url type="application/opensearchdescription+xml" rel="self" template="https://www.activ-automobiles.fr/opensearch.xml"/>
  <Image width="16" height="16" type="image/png">https://www.activ-automobiles.fr/favicon.ico</Image>
  <Language>fr-FR</Language>
  <OutputEncoding>UTF-8</OutputEncoding>
  <InputEncoding>UTF-8</InputEncoding>
</OpenSearchDescription>
